vsddcolor/__init__.py
vsddcolor/__main__.py
vsddcolor/ddcolor_arch.py
vsddcolor/ddcolor_arch_utils/__int__.py
vsddcolor/ddcolor_arch_utils/convnext.py
vsddcolor/ddcolor_arch_utils/position_encoding.py
vsddcolor/ddcolor_arch_utils/transformer.py
vsddcolor/ddcolor_arch_utils/transformer_utils.py
vsddcolor/ddcolor_arch_utils/unet.py
vsddcolor/models/ddcolor_artistic.pth
vsddcolor/models/ddcolor_modelscope.pth
vsddcolor-1.0.0.dist-info/METADATA
vsddcolor-1.0.0.dist-info/WHEEL
vsddcolor-1.0.0.dist-info/RECORD
