Metadata-Version: 2.1
Name: vsddcolor
Version: 1.0.0
Summary: DDColor function for VapourSynth
Project-URL: Homepage, https://github.com/HolyWu/vs-ddcolor
Project-URL: Bug Tracker, https://github.com/HolyWu/vs-ddcolor/issues
Author-email: HolyWu <holywu@gmail.com>
Keywords: DDColor,VapourSynth
Classifier: Operating System :: OS Independent
Classifier: Programming Language :: Python :: 3 :: Only
Classifier: Topic :: Multimedia :: Video
Requires-Python: >=3.11
Requires-Dist: kornia>=0.7.0
Requires-Dist: numpy>=1.26.2
Requires-Dist: requests>=2.31.0
Requires-Dist: timm>=0.9.12
Requires-Dist: torch>=2.1.1
Requires-Dist: tqdm>=4.66.1
Requires-Dist: vapoursynth>=62
